LICENSE
README.md
fastapi_cache/__init__.py
fastapi_cache/coder.py
fastapi_cache/context.py
fastapi_cache/decorator.py
fastapi_cache/key_builder.py
fastapi_cache/py.typed
fastapi_cache/backends/__init__.py
fastapi_cache/backends/dynamodb.py
fastapi_cache/backends/inmemory.py
fastapi_cache/backends/memcached.py
fastapi_cache/backends/redis.py
fastapi_cache/helpers/__init__.py
fastapi_cache/helpers/invariant.py
fastapi_cache/helpers/typing.py
fastapi_cache/types/__init__.py
fastapi_cache/types/backend.py
fastapi_cache/types/protocols.py
fastapi_cache2_fork-2.2.1.dist-info/METADATA
fastapi_cache2_fork-2.2.1.dist-info/WHEEL
fastapi_cache2_fork-2.2.1.dist-info/licenses/LICENSE
fastapi_cache2_fork-2.2.1.dist-info/RECORD
